ZypeC/__init__.py
ZypeC/cli.py
ZypeC/compilers.py
ZypeC-1.2.0.dist-info/LICENSE
ZypeC-1.2.0.dist-info/METADATA
ZypeC-1.2.0.dist-info/WHEEL
ZypeC-1.2.0.dist-info/entry_points.txt
ZypeC-1.2.0.dist-info/top_level.txt
ZypeC-1.2.0.dist-info/RECORD
