Metadata-Version: 2.1
Name: ZypeC
Version: 1.2.0
Summary: Zype Compilers
Home-page: https://github.com/Zype-Z/ZypeC
Author: TechGeeks
Author-email: ZypeC@tgeeks.cf
Maintainer: Rajdeep Malakar
Maintainer-email: Rajdeep@tgeeks.cf
License: UNKNOWN
Platform: UNKNOWN
Classifier: Programming Language :: Python :: 3
Classifier: License :: OSI Approved :: MIT License
Classifier: Operating System :: OS Independent
Requires-Python: >=3.6
Requires-Dist: markdown
Requires-Dist: ZypeSDK
